main.py
datantic/__init__.py
datantic/converters.py
datantic/fields.py
datantic/model.py
datantic/nesting.py
datantic/types.py
datantic/utils.py
datantic/validator.py
datantic/plugins/__init__.py
datantic/plugins/pandas.py
datantic/plugins/polars.py
datantic/validators/pandas.py
datantic/validators/polars.py
tests/conftest.py
tests/test_converters.py
tests/test_fields.py
tests/test_model.py
tests/test_nesting.py
tests/test_plugins_pandas.py
tests/test_plugins_polars.py
tests/test_types.py
tests/test_utils.py
tests/test_validator.py
tests/test_validators_pandas.py
tests/test_validators_polars.py
datantic-0.0.5.dist-info/METADATA
datantic-0.0.5.dist-info/WHEEL
datantic-0.0.5.dist-info/top_level.txt
datantic-0.0.5.dist-info/RECORD
