Metadata-Version: 2.4
Name: datantic
Version: 0.0.5
Summary: Seamlessly integrates Pydantic and Pandera, combining the expressiveness of Pydantic models with the efficiency of Pandera's DataFrame checks.
Author-email: Kevin Saltarelli <kevinqz@gmail.com>
Requires-Python: >=3.11
